bar_chart_nivo_custom/__init__.py
bar_chart_nivo_custom/example.py
bar_chart_nivo_custom/frontend/build/asset-manifest.json
bar_chart_nivo_custom/frontend/build/bootstrap.min.css
bar_chart_nivo_custom/frontend/build/bootstrap.min.css.map
bar_chart_nivo_custom/frontend/build/index.html
bar_chart_nivo_custom/frontend/build/static/css/main.3fc36394.css
bar_chart_nivo_custom/frontend/build/static/css/main.3fc36394.css.map
bar_chart_nivo_custom/frontend/build/static/js/main.135c1762.js
bar_chart_nivo_custom/frontend/build/static/js/main.135c1762.js.LICENSE.txt
bar_chart_nivo_custom/frontend/build/static/js/main.135c1762.js.map
streamlit_custom_bar_nivo-0.0.1.dist-info/LICENSE
streamlit_custom_bar_nivo-0.0.1.dist-info/METADATA
streamlit_custom_bar_nivo-0.0.1.dist-info/WHEEL
streamlit_custom_bar_nivo-0.0.1.dist-info/top_level.txt
streamlit_custom_bar_nivo-0.0.1.dist-info/RECORD
